sqlramen.py
sqlramen-0.9.3.dist-info/entry_points.txt
sqlramen-0.9.3.dist-info/WHEEL
sqlramen-0.9.3.dist-info/METADATA
sqlramen-0.9.3.dist-info/RECORD
