Metadata-Version: 2.4
Name: sqlramen
Version: 0.9.3
Summary: SQLRamen provides a convenient way to map Python objects to relational database tables, with no declarative code of any kind.  It's built on top of the SQLAlchemy ORM and provides a super-minimalistic interface to an existing database.
Author-email: julien tayon <julien@tayon.net>
Classifier: Development Status :: 5 - Production/Stable
Classifier: License :: OSI Approved :: Python Software Foundation License
Classifier: Programming Language :: Python :: 3.7
Classifier: Programming Language :: Python :: 3.8
Classifier: Programming Language :: Python :: 3.9
Classifier: Programming Language :: Python :: 3.10
Classifier: Programming Language :: Python :: 3.11
Classifier: Programming Language :: Python :: 3.12
Classifier: Programming Language :: Python :: 3.13
Classifier: Programming Language :: Python :: 3
Classifier: Operating System :: OS Independent
Classifier: Programming Language :: Python
Requires-Dist: sqlalchemy>=2.0.0
Project-URL: Changelog, https://github.com/jul/sqlramen/README.md
Project-URL: Documentation, https://github.com/jul/sqlramen/README.md
Project-URL: Homepage, https://github.com/jul/sqlramen
Project-URL: Issues, https://github.com/jul/sqlramen/issues
Project-URL: Repository, https://github.com/jul/sqlramen
